unlzw-0.1.1.dist-info/DESCRIPTION.rst
unlzw-0.1.1.dist-info/WHEEL
unlzw-0.1.1.dist-info/metadata.json
unlzw-0.1.1.dist-info/METADATA
unlzw-0.1.1.dist-info/RECORD
unlzw-0.1.1.dist-info/top_level.txt
unlzw/_unlzw_build.py
unlzw/__init__.py
unlzw/_unlzw.abi3.so
unlzw/_unlzw.c
